sapysol/__init__.py
sapysol/helpers.py
sapysol/ix.py
sapysol/jupag.py
sapysol/snippets/batcher.py
sapysol/snippets/token_selloff.py
sapysol/snippets/wallets_balance.py
sapysol/sysvar/clock.py
sapysol/token.py
sapysol/tokenMetadata2022.py
sapysol/tokenMetadataMetaplex.py
sapysol/token_cache.py
sapysol/tx.py
sapysol/wallet.py
sapysol-0.6.0.dist-info/LICENSE
sapysol-0.6.0.dist-info/METADATA
sapysol-0.6.0.dist-info/WHEEL
sapysol-0.6.0.dist-info/RECORD
