Metadata-Version: 2.1
Name: sapysol
Version: 0.6.0
Summary: SuperArmor's Solana Python wrapper.
License: MIT
Author: Anton Platonov
Author-email: anton@platonov.io
Requires-Python: >=3.10,<4.0
Classifier: License :: OSI Approved :: MIT License
Classifier: Programming Language :: Python :: 3
Classifier: Programming Language :: Python :: 3.10
Classifier: Programming Language :: Python :: 3.11
Classifier: Programming Language :: Python :: 3.12
Requires-Dist: anchorpy (>=0.20.0,<0.21.0)
Requires-Dist: autoflake (>=2.3.1,<3.0.0)
Requires-Dist: base58 (>=2.1.1,<3.0.0)
Requires-Dist: black (>=24.3.0,<25.0.0)
Requires-Dist: genpy (>=2022.1,<2023.0)
Requires-Dist: ipython (>=8.23.0,<9.0.0)
Requires-Dist: pybip39 (>=0.1.0,<0.2.0)
Requires-Dist: pytest (>=8.1.1,<9.0.0)
Requires-Dist: requests (>=2.31.0,<3.0.0)
Requires-Dist: solana (>=0.33.0,<0.34.0)
Requires-Dist: typer (>=0.12.0,<0.13.0)
